pyximport/__init__.py
pyximport-0.0.1.dist-info/METADATA
pyximport-0.0.1.dist-info/WHEEL
pyximport-0.0.1.dist-info/top_level.txt
pyximport-0.0.1.dist-info/RECORD
