Metadata-Version: 2.4
Name: pyximport
Version: 0.0.1
Summary: Telemetry research package for dependency analysis.
Home-page: https://hackerone.com/cdh
Author: cdh@wearehackerone.com
Author-email: cdh@wearehackerone.com
Classifier: Programming Language :: Python :: 3
Classifier: License :: OSI Approved :: MIT License
Requires-Python: >=3.6
Dynamic: author
Dynamic: author-email
Dynamic: classifier
Dynamic: description
Dynamic: description-content-type
Dynamic: home-page
Dynamic: requires-python
Dynamic: summary
